aio_clients/__init__.py
aio_clients/__version__.py
aio_clients/client.py
aio_clients/exceptions.py
aio_clients/multipart/__init__.py
aio_clients/multipart/main.py
aio_clients/multipart/struct.py
aio_clients/struct.py
aio_clients/types.py
aio_clients-2.1.0.dist-info/LICENSE
aio_clients-2.1.0.dist-info/METADATA
aio_clients-2.1.0.dist-info/WHEEL
aio_clients-2.1.0.dist-info/RECORD
