Metadata-Version: 2.1
Name: aio-clients
Version: 2.1.0
Summary: Python aiohttp client
Home-page: https://github.com/skar404/aio-clients
License: MIT
Author: Denis Malin
Author-email: denis@malina.page
Requires-Python: >=3.7,<4.0
Classifier: License :: OSI Approved :: MIT License
Classifier: Programming Language :: Python :: 3
Classifier: Programming Language :: Python :: 3.7
Classifier: Programming Language :: Python :: 3.8
Classifier: Programming Language :: Python :: 3.9
Classifier: Programming Language :: Python :: 3.10
Classifier: Programming Language :: Python :: 3.11
Classifier: Programming Language :: Python :: 3.12
Requires-Dist: aiohttp (>=3.8.6,<3.9) ; python_version >= "3.7" and python_version < "3.8"
Requires-Dist: aiohttp (>=3.9.3) ; python_version >= "3.8"
Project-URL: Documentation, https://github.com/skar404/aio-clients
Project-URL: Repository, https://github.com/skar404/aio-clients
